admin_utils/__init__.py
admin_utils/brief.py
admin_utils/mixins.py
admin_utils/mock.py
admin_utils/static/admin_utils/foldable-list-filter.css
admin_utils/static/admin_utils/foldable-list-filter.js
admin_utils/static/admin_utils/full-width.css
django_admin_utils-2.2.0.dist-info/licenses/LICENSE
django_admin_utils-2.2.0.dist-info/METADATA
django_admin_utils-2.2.0.dist-info/WHEEL
django_admin_utils-2.2.0.dist-info/top_level.txt
django_admin_utils-2.2.0.dist-info/RECORD
