Metadata-Version: 2.4
Name: django-admin-utils
Version: 2.2.0
Summary: Utility code and patterns.
Author-email: Ionel Cristian Mărieș <contact@ionelmc.ro>
License-Expression: BSD-2-Clause
Project-URL: Sources, https://github.com/ionelmc/django-admin-utils
Project-URL: Changelog, https://github.com/ionelmc/django-admin-utils/blob/master/CHANGELOG.rst
Project-URL: Issue Tracker, https://github.com/ionelmc/django-admin-utils/issues
Classifier: Development Status :: 5 - Production/Stable
Classifier: Intended Audience :: Developers
Classifier: Operating System :: Unix
Classifier: Operating System :: POSIX
Classifier: Operating System :: Microsoft :: Windows
Classifier: Programming Language :: Python
Classifier: Programming Language :: Python :: 3
Classifier: Programming Language :: Python :: 3 :: Only
Classifier: Programming Language :: Python :: 3.9
Classifier: Programming Language :: Python :: 3.10
Classifier: Programming Language :: Python :: 3.11
Classifier: Programming Language :: Python :: 3.12
Classifier: Programming Language :: Python :: 3.13
Classifier: Programming Language :: Python :: 3.14
Classifier: Programming Language :: Python :: Implementation :: CPython
Classifier: Programming Language :: Python :: Implementation :: PyPy
Classifier: Topic :: Utilities
Classifier: Framework :: Django
Requires-Python: >=3.9
License-File: LICENSE
Dynamic: license-file
